projecttracker/__init__.py
projecttracker/starttracker.py
projecttracker/management/__init__.py
projecttracker/management/operations.py
projecttracker/management/visualizations.py
projecttracker/utils/__init__.py
projecttracker/utils/file_handler.py
projecttracker/utils/input_handler.py
projecttracker-0.0.2.dist-info/LICENSE.txt
projecttracker-0.0.2.dist-info/METADATA
projecttracker-0.0.2.dist-info/WHEEL
projecttracker-0.0.2.dist-info/top_level.txt
projecttracker-0.0.2.dist-info/RECORD
