Metadata-Version: 2.1
Name: projecttracker
Version: 0.0.2
Summary: App for tracking projects and tasks
Author-email: Pranav Kumar Mahesh <pranava.km@gmail.com>, Natalie Crystal Coutinho <coutinho.natalie0@gmail.com>
Project-URL: Homepage, https://github.com/nccoutinho/Project-Group-13-Step-3
Classifier: Programming Language :: Python :: 3
Classifier: License :: OSI Approved :: MIT License
Classifier: Operating System :: OS Independent
Requires-Python: >=3.8
License-File: LICENSE.txt
